pypck/__init__.py
pypck/cli.py
pypckbuild-1.2.0.dist-info/METADATA
pypckbuild-1.2.0.dist-info/WHEEL
pypckbuild-1.2.0.dist-info/entry_points.txt
pypckbuild-1.2.0.dist-info/top_level.txt
pypckbuild-1.2.0.dist-info/RECORD
