Metadata-Version: 2.4
Name: pypckbuild
Version: 1.2.0
Summary: Package Builder
Author-email: Mxtsouko <mixtrex62@gmail.com>
License: MIT
Requires-Python: >=3.10
